Metadata-Version: 2.1
Name: odoo14-addon-auth_oidc
Version: 14.0.1.2.0
Summary: Allow users to login through OpenID Connect Provider
Home-page: https://github.com/OCA/server-auth
Author: ICTSTUDIO, André Schenkels, ACSONE SA/NV, Odoo Community Association (OCA)
Author-email: support@odoo-community.org
License: AGPL-3
Classifier: Programming Language :: Python
Classifier: Framework :: Odoo
Classifier: Framework :: Odoo :: 14.0
Classifier: License :: OSI Approved :: GNU Affero General Public License v3
Requires-Python: >=3.6
Requires-Dist: odoo <14.1dev,>=14.0a
Requires-Dist: python-jose
